cloud_cost_allocation/__init__.py
cloud_cost_allocation/cloud_cost_allocator.py
cloud_cost_allocation/config.py
cloud_cost_allocation/cost_items.py
cloud_cost_allocation/exceptions.py
cloud_cost_allocation/main.py
cloud_cost_allocation/reader/__init__.py
cloud_cost_allocation/reader/azure_ea_amortized_cost_reader.py
cloud_cost_allocation/reader/base_reader.py
cloud_cost_allocation/reader/csv_allocated_cost_reader.py
cloud_cost_allocation/reader/csv_cost_allocation_keys_reader.py
cloud_cost_allocation/reader/csv_focus_reader.py
cloud_cost_allocation/utils/__init__.py
cloud_cost_allocation/utils/utils.py
cloud_cost_allocation/writer/__init__.py
cloud_cost_allocation/writer/base_writer.py
cloud_cost_allocation/writer/csv_allocated_cost_writer.py
cloud_cost_allocation-2.3.1.dist-info/licenses/LICENSE
cloud_cost_allocation-2.3.1.dist-info/METADATA
cloud_cost_allocation-2.3.1.dist-info/WHEEL
cloud_cost_allocation-2.3.1.dist-info/top_level.txt
cloud_cost_allocation-2.3.1.dist-info/RECORD
