Metadata-Version: 2.4
Name: cloud-cost-allocation
Version: 2.3.1
Summary: Python library for shared, hierarchical cost allocation based on user-defined usage metrics.
Home-page: https://github.com/AmadeusITGroup/cloud-cost-allocation
Author: Marc Perreaut
Author-email: marc.perreaut@amadeus.com
Maintainer: Amadeus IT Group
Maintainer-email: opensource@amadeus.com
License: MIT license
Project-URL: Issue Tracker, https://github.com/AmadeusITGroup/cloud-cost-allocation/issues
Keywords: finops,cloud cost allocation
Classifier: Development Status :: 2 - Pre-Alpha
Classifier: Intended Audience :: Developers
Classifier: License :: OSI Approved :: MIT License
Classifier: Operating System :: OS Independent
Classifier: Programming Language :: Python
Classifier: Programming Language :: Python :: 3
Classifier: Programming Language :: Python :: 3.5
Classifier: Programming Language :: Python :: 3.6
Classifier: Programming Language :: Python :: 3.7
Classifier: Programming Language :: Python :: 3.8
Classifier: Programming Language :: Python :: 3.9
Classifier: Programming Language :: Python :: 3.10
Classifier: Topic :: Office/Business :: Financial
License-File: LICENSE
Dynamic: classifier
Dynamic: description
Dynamic: description-content-type
Dynamic: home-page
Dynamic: license
Dynamic: license-file
Dynamic: maintainer
Dynamic: maintainer-email
Dynamic: summary
